pseudomatic/__init__.py
pseudomatic/__main__.py
pseudomatic/names.py
pseudomatic-0.1.3.dist-info/METADATA
pseudomatic-0.1.3.dist-info/WHEEL
pseudomatic-0.1.3.dist-info/licenses/LICENSE
pseudomatic-0.1.3.dist-info/RECORD
