Metadata-Version: 2.4
Name: pseudomatic
Version: 0.1.3
Summary: A tool for generating deterministic pseudonyms based on a seed string and selected language
Project-URL: Homepage, https://github.com/OpenMindUA/pseudomatic
Project-URL: Repository, https://github.com/OpenMindUA/pseudomatic
Project-URL: Documentation, https://github.com/OpenMindUA/pseudomatic#readme
License-Expression: MIT
License-File: LICENSE
Keywords: anonymization,generator,pseudonym
Classifier: Development Status :: 3 - Alpha
Classifier: License :: OSI Approved :: MIT License
Classifier: Operating System :: OS Independent
Classifier: Programming Language :: Python :: 3
Classifier: Programming Language :: Python :: 3.10
Classifier: Programming Language :: Python :: 3.11
Classifier: Programming Language :: Python :: 3.12
Requires-Python: >=3.10
